mimic_replay/__init__.py
mimic_replay/config.py
mimic_replay/injector.py
mimic_replay/install.py
mimic_replay-1.1.6.dist-info/LICENSE
mimic_replay-1.1.6.dist-info/METADATA
mimic_replay-1.1.6.dist-info/WHEEL
mimic_replay-1.1.6.dist-info/top_level.txt
mimic_replay-1.1.6.dist-info/RECORD
